CHANGELOG.md
LICENSE
README.md
aerich/__init__.py
aerich/cli.py
aerich/coder.py
aerich/ddl/__init__.py
aerich/ddl/mysql/__init__.py
aerich/ddl/postgres/__init__.py
aerich/ddl/sqlite/__init__.py
aerich/enums.py
aerich/exceptions.py
aerich/inspectdb/__init__.py
aerich/inspectdb/mysql.py
aerich/inspectdb/postgres.py
aerich/inspectdb/sqlite.py
aerich/migrate.py
aerich/models.py
aerich/utils.py
aerich/version.py
myaerich-0.7.3.dist-info/LICENSE
myaerich-0.7.3.dist-info/METADATA
myaerich-0.7.3.dist-info/WHEEL
myaerich-0.7.3.dist-info/entry_points.txt
myaerich-0.7.3.dist-info/RECORD
