Metadata-Version: 2.1
Name: myaerich
Version: 0.7.3
Summary: A database migrations tool for Tortoise ORM.
Home-page: https://github.com/tortoise/aerich
License: Apache-2.0
Keywords: migrate,Tortoise-ORM,mysql
Author: long2ice
Author-email: long2ice@gmail.com
Requires-Python: >=3.7,<4.0
Classifier: License :: OSI Approved :: Apache Software License
Classifier: Programming Language :: Python :: 3
Classifier: Programming Language :: Python :: 3.7
Classifier: Programming Language :: Python :: 3.8
Classifier: Programming Language :: Python :: 3.9
Classifier: Programming Language :: Python :: 3.10
Classifier: Programming Language :: Python :: 3.11
Classifier: Programming Language :: Python :: 3.12
Provides-Extra: asyncmy
Provides-Extra: asyncpg
Requires-Dist: asyncmy (>=0.2.8rc1,<0.3.0) ; extra == "asyncmy"
Requires-Dist: asyncpg ; extra == "asyncpg"
Requires-Dist: click
Requires-Dist: dictdiffer
Requires-Dist: pydantic (>=2.0,<3.0)
Requires-Dist: tomlkit
Requires-Dist: tortoise-orm
Project-URL: Documentation, https://github.com/tortoise/aerich
Project-URL: Repository, https://github.com/tortoise/aerich.git
